confluence/Confluence.py
confluence/__init__.py
confluence/__main__.py
dohq_confluence-1.0.4.dist-info/DESCRIPTION.rst
dohq_confluence-1.0.4.dist-info/METADATA
dohq_confluence-1.0.4.dist-info/RECORD
dohq_confluence-1.0.4.dist-info/WHEEL
dohq_confluence-1.0.4.dist-info/entry_points.txt
dohq_confluence-1.0.4.dist-info/metadata.json
dohq_confluence-1.0.4.dist-info/top_level.txt
dohq_confluence-1.0.4.dist-info/zip-safe
