Metadata-Version: 2.0
Name: dohq-confluence
Version: 1.0.4
Summary: This is API to work with Atlassian Confluence (WIKI system). See more: https://devopshq.github.io/confluence/
Home-page: https://devopshq.github.io/confluence/
Author: Open DevOps Community
Author-email: tim55667757@gmail.com
License: MIT
Download-URL: https://github.com/devopshq/confluence.git
Keywords: confluence,api,DevOpsHQ,devops,wikiatlassian
Platform: UNKNOWN
Classifier: Development Status :: 5 - Production/Stable
Classifier: Environment :: Console
Classifier: Intended Audience :: Developers
Classifier: Topic :: Utilities
Classifier: License :: OSI Approved :: MIT License
Classifier: Natural Language :: Russian
Classifier: Programming Language :: Python :: 3.6
